pyvalidex/__init__.py
pyvalidex/validator.py
pyvalidex-0.1.1.dist-info/licenses/LICENSE
pyvalidex-0.1.1.dist-info/METADATA
pyvalidex-0.1.1.dist-info/WHEEL
pyvalidex-0.1.1.dist-info/top_level.txt
pyvalidex-0.1.1.dist-info/RECORD
