Metadata-Version: 2.4
Name: pyvalidex
Version: 0.1.1
Summary: Python library to validate Indian identifiers like PAN, Aadhaar, GSTIN, and IFSC.
Author-email: "Jobin Jose (PyPI: codedbyjobin)" <jobinj5210@gmail.com>
License: MIT
Requires-Python: >=3.8
License-File: LICENSE
Dynamic: license-file
